{
  "project_info": {
    "project_number": "844422235247",
    "firebase_url": "https://pruebaflutter-33936.firebaseio.com",
    "project_id": "pruebaflutter-33936",
    "storage_bucket": "pruebaflutter-33936.appspot.com"
  },
  "client": [
    {
      "client_info": {
        "mobilesdk_app_id": "1:844422235247:android:e8a0e8135defac8ad4799a",
        "android_client_info": {
          "package_name": "com.example.prueba"
        }
      },
      "oauth_client": [
        {
          "client_id": "844422235247-c1jro6jh0llo3q904n0qmsvpi6b8aqvk.apps.googleusercontent.com",
          "client_type": 3
        }
      ],
      "api_key": [
        {
          "current_key": "AIzaSyCahzt7cBoK9chEUW0Lwa9NkNMLIAkGPjs"
        }
      ],
      "services": {
        "appinvite_service": {
          "other_platform_oauth_client": [
            {
              "client_id": "844422235247-c1jro6jh0llo3q904n0qmsvpi6b8aqvk.apps.googleusercontent.com",
              "client_type": 3
            }
          ]
        }
      }
    },
    {
      "client_info": {
        "mobilesdk_app_id": "1:844422235247:android:05f397a55c668881d4799a",
        "android_client_info": {
          "package_name": "com.pruebaflutter.flutter"
        }
      },
      "oauth_client": [
        {
          "client_id": "844422235247-c1jro6jh0llo3q904n0qmsvpi6b8aqvk.apps.googleusercontent.com",
          "client_type": 3
        }
      ],
      "api_key": [
        {
          "current_key": "AIzaSyCahzt7cBoK9chEUW0Lwa9NkNMLIAkGPjs"
        }
      ],
      "services": {
        "appinvite_service": {
          "other_platform_oauth_client": [
            {
              "client_id": "844422235247-c1jro6jh0llo3q904n0qmsvpi6b8aqvk.apps.googleusercontent.com",
              "client_type": 3
            }
          ]
        }
      }
    }
  ],
  "configuration_version": "1"
}